lightweight_charts/__init__.py
lightweight_charts/abstract.py
lightweight_charts/chart.py
lightweight_charts/polygon.py
lightweight_charts/table.py
lightweight_charts/toolbox.py
lightweight_charts/topbar.py
lightweight_charts/util.py
lightweight_charts/widgets.py
lightweight_charts/js/callback.js
lightweight_charts/js/funcs.js
lightweight_charts/js/pkg.js
lightweight_charts/js/table.js
lightweight_charts/js/toolbox.js
lightweight_charts_2-0.9.9.dist-info/METADATA
lightweight_charts_2-0.9.9.dist-info/WHEEL
lightweight_charts_2-0.9.9.dist-info/top_level.txt
lightweight_charts_2-0.9.9.dist-info/RECORD
