Metadata-Version: 2.1
Name: lightweight-charts-2
Version: 0.9.9
Summary: Lightweight charts but you can have optional parameters of naming each popup window
Home-page: https://github.com/yourusername/lightweight_charts_2
Author: Jimmy Fallon
Author-email: ashzarz.56@gmail.com
Requires-Python: >=3.8
Requires-Dist: pandas
Requires-Dist: pywebview >=4.3
